docs/Makefile
docs/basic_interface.rst
docs/conf.py
docs/index.rst
docs/install.rst
docs/make.bat
docs/maps.rst
docs/modules.rst
docs/projections.rst
docs/quickstart.rst
docs/requirements.txt
docs/surveys.rst
docs/images/AlbersSkyproj_with_indicatrix.png
docs/images/BLISS_survey.png
docs/images/DECaLS_survey.png
docs/images/DESAlbers_survey_with_indicatrices.png
docs/images/DES_survey.png
docs/images/DES_survey_with_indicatrices.png
docs/images/EqualEarthSkyproj_with_indicatrices.png
docs/images/GnomonicSkyproj_with_indicatrix.png
docs/images/HammerSkyproj_with_indicatrices.png
docs/images/LaeaSkyproj_with_indicatrices.png
docs/images/MagLiTeS_survey.png
docs/images/McBrydeSkyproj_with_indicatrices.png
docs/images/MollweideSkyproj_with_indicatrices.png
docs/images/ObliqueMollweideSkyproj.png
docs/images/Roman_HLWAS_survey.png
docs/images/Skyproj_with_indicatrices.png
docs/images/healsparse_one.png
docs/images/healsparse_two.png
docs/images/healsparse_valid_pixels.png
docs/images/hpxbin.png
docs/images/hpxbin_reproject.png
docs/images/lines_and_polygons_0.0.png
docs/images/milky_way.png
docs/images/milky_way_galactic.png
docs/images/skyproj_full_override_sizes.png
skyproj/__init__.py
skyproj/_docstrings.py
skyproj/_skyproj.py
skyproj/_version.py
skyproj/hpx_utils.py
skyproj/mpl_utils.py
skyproj/skyaxes.py
skyproj/skycrs.py
skyproj/skygrid.py
skyproj/skyproj.py
skyproj/survey.py
skyproj/transforms.py
skyproj/utils.py
skyproj/data/bliss-poly.txt
skyproj/data/ccd_corners_xy_fill.dat
skyproj/data/constellationsANDstars.json
skyproj/data/decals-poly.txt
skyproj/data/derosita-poly.txt
skyproj/data/des-round13-poly.txt
skyproj/data/des-round17-poly.txt
skyproj/data/des-round19-poly.txt
skyproj/data/macho_corners_xy.dat
skyproj/data/maglites-poly.txt
skyproj/data/roman-hlwas-poly.txt
skyproj/data/smash_fields_final.txt
skyproj-2.2.0.dist-info/licenses/LICENSE
tutorial/README.md
tutorial/tutorial_baseclass.ipynb
tutorial/tutorial_healsparse.ipynb
tutorial/tutorial_surveys.ipynb
ups/skyproj.table
skyproj-2.2.0.dist-info/METADATA
skyproj-2.2.0.dist-info/WHEEL
skyproj-2.2.0.dist-info/top_level.txt
skyproj-2.2.0.dist-info/zip-safe
skyproj-2.2.0.dist-info/RECORD
