Metadata-Version: 2.4
Name: skyproj
Version: 2.2.0
Summary: Python tools for making sky projections and maps
Author: Alex Drlica-Wagner, others
Author-email: Eli Rykoff <erykoff@stanford.edu>
License: BSD 3-Clause License
Project-URL: home, https://github.com/lsstdesc/skyproj
Classifier: Intended Audience :: Science/Research
Classifier: License :: OSI Approved :: BSD License
Classifier: Operating System :: OS Independent
Classifier: Programming Language :: Python :: 3
Classifier: Programming Language :: Python :: 3.7
Classifier: Topic :: Scientific/Engineering :: Astronomy
Requires-Python: >=3.9
License-File: LICENSE
Requires-Dist: astropy>=4.0
Requires-Dist: matplotlib>=3.8
Requires-Dist: hpgeom
Requires-Dist: healsparse
Requires-Dist: pyproj>=3.1
Requires-Dist: numpy
Dynamic: license-file
